setup.py
mao2116/__init__.py
mao2116/mao2116.py
mao2116.egg-info/PKG-INFO
mao2116.egg-info/SOURCES.txt
mao2116.egg-info/dependency_links.txt
mao2116.egg-info/not-zip-safe
mao2116.egg-info/top_level.txt