Metadata-Version: 2.1
Name: mao2116
Version: 0.1
Summary: FUCK ALL
Home-page: UNKNOWN
Author: Mao2116
License: UNKNOWN
Platform: UNKNOWN
